{
    "version": "nightly",
    "homepage": "http://leagueoflegends.com/",
    "description": "MOBA game published by Riot Games.",
    "license": {
        "identifier": "Freeware",
        "url": "https://euw.leagueoflegends.com/en/legal/termsofuse"
    },
    "url": "https://riotgamespatcher-a.akamaihd.net/releases/live/installer/deploy/League%20of%20Legends%20installer%20EUW.exe#/installer_euw.exe",
    "persist": [
        "Config"
    ],
    "shortcuts": [
        ["LeagueClient.exe", "League of Legends"]
    ],
    "installer": {
        "##": "Uses a BitRock installer",
        "script": [
            "if (Test-Path ($desktopLink = \"$Env:PUBLIC\\Desktop\\League of Legends.lnk\")) {$desktopLink = ''}",
            "if (Test-Path ($startMenuDir = \"$Env:PROGRAMDATA\\Microsoft\\Windows\\Start Menu\\Programs\\League of Legends\")) {$startMenuDir = ''}",
            "Start-Process \"$dir\\installer_euw.exe\" -ArgumentList \"--mode unattended --installdir `\"$dir`\" --license_agreement 1\" -Verb RunAs -Wait",
            "if ($desktopLink) {Remove-Item $desktopLink}",
            "if ($startMenuDir) {Remove-Item $startMenuDir -Recurse}"
        ]
    },
    "uninstaller": {
        "script": "Start-Process -FilePath \"$dir\\Uninstall League of Legends.exe\" -ArgumentList \"--mode unattended\" -Verb RunAs -Wait"
    }
}
